README.txt
bootstrap.py
buildout.cfg
setup.py
Products/__init__.py
Products.HSCustom.egg-info/PKG-INFO
Products.HSCustom.egg-info/SOURCES.txt
Products.HSCustom.egg-info/dependency_links.txt
Products.HSCustom.egg-info/entry_points.txt
Products.HSCustom.egg-info/namespace_packages.txt
Products.HSCustom.egg-info/not-zip-safe
Products.HSCustom.egg-info/paster_plugins.txt
Products.HSCustom.egg-info/requires.txt
Products.HSCustom.egg-info/top_level.txt
Products/HSCustom/HISTORY.txt
Products/HSCustom/LICENSE.txt
Products/HSCustom/TODO.txt
Products/HSCustom/__init__.py
Products/HSCustom/config.py
Products/HSCustom/version.txt
Products/HSCustom/Extensions/Install.py
Products/HSCustom/Extensions/__init__.py
Products/HSCustom/Extensions/utils.py
Products/HSCustom/skins/hscustom_images/hscustom_bg1.gif
Products/HSCustom/skins/hscustom_images/hscustom_bg2.gif
Products/HSCustom/skins/hscustom_images/logo.gif
Products/HSCustom/skins/hscustom_styles/base_properties.props
Products/HSCustom/skins/hscustom_styles/hscustom.css.dtml
Products/HSCustom/skins/hscustom_templates/login_form.cpt
Products/HSCustom/skins/hscustom_templates/login_form.cpt.metadata
Products/HSCustom/skins/hscustom_templates/undo_form.pt
Products/HSCustom/skins/hscustom_templates/undo_form.pt.metadata
Products/HSCustom/tests/__init__.py
Products/HSCustom/tests/framework.py
Products/HSCustom/tests/runalltests.py
Products/HSCustom/tests/testSkeleton.py
Products/HSCustom/tests/testStyleInstallation.py
docs/HISTORY.txt
docs/LICENSE.GPL
docs/LICENSE.txt