Metadata-Version: 1.0
Name: Products.HSCustom
Version: 0.2
Summary: The HSCustom theme was originally created for my band's website.
Home-page: http://svn.plone.org/svn/collective/Products.HSCustom/
Author: Alex Clark
Author-email: aclark@aclark.net
License: GPL
Platform: UNKNOWN
Classifier: Framework :: Plone
Classifier: Programming Language :: Python
Classifier: Topic :: Software Development :: Libraries :: Python Modules
